autograd_gamma/__init__.py
autograd_gamma-0.4.1.dist-info/LICENSE
autograd_gamma-0.4.1.dist-info/METADATA
autograd_gamma-0.4.1.dist-info/WHEEL
autograd_gamma-0.4.1.dist-info/top_level.txt
autograd_gamma-0.4.1.dist-info/RECORD
