Metadata-Version: 2.1
Name: autograd-gamma
Version: 0.4.1
Summary: Autograd compatible approximations to the gamma family of functions
Home-page: https://github.com/CamDavidsonPilon/autograd-gamma
Author: Cameron Davidson-Pilon
Author-email: cam.davidson.pilon@gmail.com
License: UNKNOWN
Keywords: autograd,gamma,incomplete gamma function
Platform: UNKNOWN
Classifier: Intended Audience :: Science/Research
Classifier: Topic :: Scientific/Engineering
Classifier: Programming Language :: Python :: 2
Classifier: Programming Language :: Python :: 3
